flitsmeister/__init__.py
flitsmeister/flitsmeister.py
flitsmeister/models.py
flitsmeister/py.typed
python_fm-1.0.0b1.dist-info/LICENSE
python_fm-1.0.0b1.dist-info/METADATA
python_fm-1.0.0b1.dist-info/WHEEL
python_fm-1.0.0b1.dist-info/RECORD
