Metadata-Version: 2.1
Name: python-fm
Version: 1.0.0b1
Summary: Asynchronous Python client for Flitsmeister
Home-page: https://github.com/DCSBL/python-flitsmeister
License: Apache-2.0
Author: DCSBL
Maintainer: DCSBL
Requires-Python: >=3.9,<4.0
Classifier: License :: OSI Approved :: Apache Software License
Classifier: Programming Language :: Python :: 3
Classifier: Programming Language :: Python :: 3.9
Classifier: Programming Language :: Python :: 3.10
Classifier: Programming Language :: Python :: 3.11
Classifier: Programming Language :: Python :: 3.12
Requires-Dist: aiohttp (>=3.0.0)
Requires-Dist: async-timeout (>=4.0.3,<5.0.0)
Requires-Dist: pyjwt (>=2.8.0,<3.0.0)
Project-URL: Bug Tracker, https://github.com/DCSBL/python-flitsmeister/issues
Project-URL: Changelog, https://github.com/DCSBL/python-flitsmeister/releases
Project-URL: Documentation, https://github.com/DCSBL/python-flitsmeister
Project-URL: Repository, https://github.com/DCSBL/python-flitsmeister
